edgelab/__init__.py
edgelab/api/__init__.py
edgelab/api/auth.py
edgelab/api/client.py
edgelab/api/exceptions.py
edgelab/cli.py
edgelab/commands/__init__.py
edgelab/commands/analyze.py
edgelab/commands/auth.py
edgelab/commands/marketplace/__init__.py
edgelab/commands/marketplace/fork.py
edgelab/commands/marketplace/list.py
edgelab/commands/marketplace/show.py
edgelab/commands/results.py
edgelab/commands/workspace.py
edgelab/config/__init__.py
edgelab/config/settings.py
edgelab/examples/__init__.py
edgelab/examples/ema_crossover.py
edgelab/examples/simple_rsi.py
edgelab/utils/__init__.py
edgelab/utils/console.py
edgelab/utils/indicator_extractor.py
edgelab-0.1.5.dist-info/METADATA
edgelab-0.1.5.dist-info/WHEEL
edgelab-0.1.5.dist-info/entry_points.txt
edgelab-0.1.5.dist-info/RECORD
