Metadata-Version: 2.4
Name: edgelab
Version: 0.1.5
Summary: EdgeLab CLI - Algorithmic trading strategy analysis platform
License: MIT
Keywords: trading,backtesting,algorithmic-trading,quantitative-finance
Author: EdgeLab Team
Requires-Python: >=3.11,<4.0
Classifier: Development Status :: 3 - Alpha
Classifier: Intended Audience :: Developers
Classifier: Intended Audience :: Financial and Insurance Industry
Classifier: License :: OSI Approved :: MIT License
Classifier: Programming Language :: Python :: 3
Classifier: Programming Language :: Python :: 3.11
Classifier: Programming Language :: Python :: 3.12
Classifier: Programming Language :: Python :: 3.13
Classifier: Programming Language :: Python :: 3.14
Classifier: Topic :: Office/Business :: Financial :: Investment
Requires-Dist: click (>=8.1.7,<9.0.0)
Requires-Dist: pydantic (>=2.5.0,<3.0.0)
Requires-Dist: pydantic-settings (>=2.1.0,<3.0.0)
Requires-Dist: python-dateutil (>=2.8.2,<3.0.0)
Requires-Dist: requests (>=2.31.0,<3.0.0)
Requires-Dist: rich (>=13.7.0,<14.0.0)
Requires-Dist: rich-click (>=1.7.3,<2.0.0)
Project-URL: Homepage, https://edgelab.com
Project-URL: Repository, https://github.com/karthik446/edgelab-cli
